aircalc.py
aircalc-0.0.8.dist-info/METADATA
aircalc-0.0.8.dist-info/WHEEL
aircalc-0.0.8.dist-info/entry_points.txt
aircalc-0.0.8.dist-info/top_level.txt
aircalc-0.0.8.dist-info/RECORD
