Metadata-Version: 2.1
Name: aircalc
Version: 0.0.8
Summary: aircalc: calculate a math expression by five fingers in air.
Home-page: https://github.com/y-takefuji/air_calculator
Author: yoshiyasu takefuji
Author-email: takefuji@keio.jp
Project-URL: Bug Tracker, https://github.com/y-takefuji/air_calculator
Classifier: Programming Language :: Python :: 3
Classifier: License :: OSI Approved :: MIT License
Classifier: Operating System :: OS Independent
Requires-Python: >=3.8
